eds_ds_tools/__init__.py
eds_ds_tools/_amazonathena.py
eds_ds_tools/_amazons3.py
eds_ds_tools/_claimcenter.py
eds_ds_tools/_config.py
eds_ds_tools/_datetime.py
eds_ds_tools/_genesys.py
eds_ds_tools/_imports.py
eds_ds_tools/_policycenter.py
eds_ds_tools/_salesforce.py
eds_ds_tools/_teradata.py
eds_ds_tools-0.8.dist-info/METADATA
eds_ds_tools-0.8.dist-info/WHEEL
eds_ds_tools-0.8.dist-info/top_level.txt
eds_ds_tools-0.8.dist-info/RECORD
