Metadata-Version: 2.1
Name: eds_ds_tools
Version: 0.8
Summary: tools for data science
Author-email: wenleicao@gmail.com
